gamesutil/__init__.py
gamesutil/__main__.py
gamesutil/config/log_config.yaml
gamesutil/core/__init__.py
gamesutil/core/agent.py
gamesutil/core/prompt.py
gamesutil/dto/__init__.py
gamesutil/dto/bootstrap_paths_dto.py
gamesutil/dto/save_manifest_dto.py
gamesutil/dto/user_instructions_dto.py
gamesutil/enums/__init__.py
gamesutil/enums/user_request.py
gamesutil/exception/__init__.py
gamesutil/exception/bootstrap_error.py
gamesutil/exception/unexpected_argument_error.py
gamesutil/exception/user_error.py
gamesutil/schemas/v1/save_manifest_schema.json
gamesutil/schemas/v2/save_manifest_schema.json
gamesutil/util/__init__.py
gamesutil/util/file_importer.py
gamesutil/util/gamesutil_logger.py
gamesutil/util/static.py
gamesutil-2.1.0.dist-info/licenses/LICENSE
gamesutil-2.1.0.dist-info/METADATA
gamesutil-2.1.0.dist-info/WHEEL
gamesutil-2.1.0.dist-info/entry_points.txt
gamesutil-2.1.0.dist-info/top_level.txt
gamesutil-2.1.0.dist-info/RECORD
