Metadata-Version: 2.4
Name: gamesutil
Version: 2.1.0
Author-email: Carlos Florez <carlos@florez.co.uk>
Maintainer-email: Carlos Florez <carlos@florez.co.uk>
License: MIT License
Project-URL: Repository, https://github.com/florez-carlos/gamesutil
Classifier: Development Status :: 5 - Production/Stable
Classifier: Programming Language :: Python :: 3.12
Requires-Python: >=3.12.10
License-File: LICENSE
Requires-Dist: pyyaml==6.0.1
Requires-Dist: toml==0.10.2
Requires-Dist: pywin32==306; sys_platform == "win32"
Requires-Dist: jsonschema==4.23.0
Requires-Dist: colorlog==6.4.0
Dynamic: license-file
